{"color_data":{},"library_state":{"panel_width":226,"sort_column":"name","sort_direction":"ascending","column_widths":[100,100,100],"open_directories":[]},"drive_publish_data":{"name":"ds-test","minify":true,"inline_files":true,"create_zip":null,"polite_load":true,"export_mozilla":true,"export_no_prefix":true,"unpack_groups":true,"add_border":false,"border_color":"rgba(0,0,0,1)","location":""},"local_publish_data":{"location":"/Users/sheadarlison/Documents/ds-test/","name":"ds-test","minify":true,"inline_files":true,"create_zip":true,"polite_load":true,"export_mozilla":true,"export_no_prefix":true,"unpack_groups":true,"add_border":false,"border_color":"rgba(0,0,0,1)"}}